invar_runtime/__init__.py
invar_runtime/contracts.py
invar_runtime/decorators.py
invar_runtime/invariant.py
invar_runtime/relations.py
invar_runtime/resource.py
invar_runtime-1.3.0.dist-info/METADATA
invar_runtime-1.3.0.dist-info/WHEEL
invar_runtime-1.3.0.dist-info/licenses/LICENSE
invar_runtime-1.3.0.dist-info/RECORD
