Metadata-Version: 2.4
Name: invar-runtime
Version: 1.3.0
Summary: Lightweight runtime contracts for Invar projects
Project-URL: Homepage, https://github.com/tefx/invar
Project-URL: Documentation, https://github.com/tefx/invar#readme
Project-URL: Repository, https://github.com/tefx/invar
Project-URL: Issues, https://github.com/tefx/invar/issues
Author: Invar Team
License-Expression: Apache-2.0
License-File: LICENSE
Keywords: contracts,design-by-contract,runtime,validation
Classifier: Development Status :: 4 - Beta
Classifier: Intended Audience :: Developers
Classifier: License :: OSI Approved :: Apache Software License
Classifier: Programming Language :: Python :: 3
Classifier: Programming Language :: Python :: 3.11
Classifier: Programming Language :: Python :: 3.12
Classifier: Topic :: Software Development :: Quality Assurance
Classifier: Typing :: Typed
Requires-Python: >=3.11
Requires-Dist: deal>=4.0
